setup.py
pametis/__init__.py
pametis/__main__.py
pametis/pametis.py
pametis/pametis_cache.py
pametis/pametis_spider.py
pametis.egg-info/PKG-INFO
pametis.egg-info/SOURCES.txt
pametis.egg-info/dependency_links.txt
pametis.egg-info/top_level.txt
test/test.py