Metadata-Version: 1.1
Name: pametis
Version: 0.4
Summary: Sitemap Analyzer/Parser/Iterator
Home-page: https://github.com/avnr/pametis
Author: Avner Herskovits
Author-email: avnr_ at outlook.com
License: UNKNOWN
Download-URL: https://github.com/avnr/pametis/tarball/0.4
Platform: UNKNOWN
Classifier: Development Status :: 4 - Beta
Classifier: Environment :: Web Environment
Classifier: Environment :: No Input/Output (Daemon)
Classifier: Environment :: Other Environment
Classifier: Intended Audience :: Developers
Classifier: Intended Audience :: Information Technology
Classifier: Intended Audience :: System Administrators
Classifier: License :: OSI Approved :: MIT License
Classifier: Operating System :: OS Independent
Classifier: Programming Language :: Python
Classifier: Topic :: Communications
